TermGFX/__init__.py
TermGFX/colors.py
TermGFX/engine.py
TermGFX/gol.py
TermGFX/lines.py
TermGFX/rects.py
TermGFX/shapes.py
TermGFX/test.py
TermGFX-0.2.0.dist-info/LICENSE
TermGFX-0.2.0.dist-info/METADATA
TermGFX-0.2.0.dist-info/WHEEL
TermGFX-0.2.0.dist-info/top_level.txt
TermGFX-0.2.0.dist-info/RECORD
