Metadata-Version: 2.1
Name: TermGFX
Version: 0.2.0
Summary: Terminal graphics with zero deps
Home-page: https://github.com/Froloket64/TermGFX
Author: Froloket64
Author-email: ket.frol2006@gmail.com
Project-URL: Bug Tracker, https://github.com/Froloket64/TermGFX/issues
Classifier: Programming Language :: Python :: 3
Classifier: License :: OSI Approved :: MIT License
Classifier: Operating System :: OS Independent
Requires-Python: >=3.6
License-File: LICENSE
